{"title":"V LIVE ─ 홈 ─ CHARTS TOP3","url":"https://www.vlive.tv/home/chart?sub=VIDEO&period=HOUR_24&country=ALL&lang=ko","favicon":"https://www.vlive.tv/home/favicon.ico","elements":[{"title":"ARTIST-MADE COLLECTION 'SHOW' BY BTS - Jimin","contents":"BTS","link":"https://www.vlive.tv/video/274752","retrieved":1642329894968,"image":"https://v-phinf.pstatic.net/20220115_243/1642200774877gpMw3_JPEG/upload_8628035023478190451158d97-51de-4cfc-9992-c0e72219827c.jpg?type=f380_213_wp"},{"title":"HAPPY BOO's DAY 🍊","contents":"SEVENTEEN","link":"https://www.vlive.tv/video/274812","retrieved":1642329894971,"image":"https://v-phinf.pstatic.net/20220116_6/1642329326302o2gOv_JPEG/upload_8640905930928379765632104-67ea-44dd-b9f6-3714fc3c08d1.jpg?type=f380_213_wp"},{"title":"ARTIST-MADE COLLECTION BY BTS 'Making-of Log' from Jimin","contents":"BTS","link":"https://www.vlive.tv/video/274836","retrieved":1642398124050,"image":"https://v-phinf.pstatic.net/20220117_246/1642381648243TekFO_JPEG/upload_864609791141190217b5ada59-b66d-4e51-b59d-8864da74e160.jpg?type=f380_213_wp"}]}