{"title":"V LIVE ─ 홈 ─ CHARTS","url":"https://www.vlive.tv/home/chart?sub=VIDEO&period=HOUR_24&country=ALL&lang=ko","favicon":"https://www.vlive.tv/home/favicon.ico","elements":[{"title":"BLACKPINK - ‘Pink Venom’ Visualizer","contents":"BLACKPINK","link":"https://www.vlive.tv/video/290345","retrieved":1661510774000,"image":"https://v-phinf.pstatic.net/20220826_79/1661493057220xQ1P2_JPEG/upload_105572697271932345660efdc6-66ff-4cb0-bb0f-2dea888d03d1.jpg?type=f228_128_wp"},{"title":"[Stray Kids(스트레이 키즈) : SKZ-TALKER GO! Season 3 (슼즈토커 고! 시즌 3)] Ep.04 CHICAGO","contents":"Stray Kids","link":"https://www.vlive.tv/video/290364","retrieved":1661522066059,"image":"https://v-phinf.pstatic.net/20220826_290/1661505407083mWjen_JPEG/upload_1055842014518518222243223c-2dec-46bb-a239-4684228aa309.jpg?type=f228_128_wp"},{"title":"BLACKPINK - ‘Pink Venom’ M/V REACTION","contents":"BLACKPINK","link":"https://www.vlive.tv/video/290274","retrieved":1661533230048,"image":"https://v-phinf.pstatic.net/20220826_5/1661482206403snk2a_JPEG/upload_105495591936040635183d7eb0-7cb3-42c4-8277-cfb1fca3bb8d.jpg?type=f228_128_wp"},{"title":"BLACKPINK WORLD TOUR [BORN PINK] SEOUL MESSAGE VIDEO","contents":"BLACKPINK","link":"https://www.vlive.tv/video/290325","retrieved":1661494904773,"image":"https://v-phinf.pstatic.net/20220826_246/166148080065443P9j_JPEG/upload_105560493528609984186541c0-ff92-4c09-9981-927f0dbc268f.jpg?type=f228_128_wp"}]}