{"title":"V LIVE ─ 홈 ─ CHARTS","url":"https://www.vlive.tv/home/chart?sub=VIDEO&period=HOUR_24&country=ALL&lang=ko","favicon":"https://www.vlive.tv/home/favicon.ico","elements":[{"title":"🐯","contents":"SEVENTEEN","link":"https://www.vlive.tv/video/275031","retrieved":1642668257696,"image":"https://v-phinf.pstatic.net/20220119_254/1642580114117Rssdj_JPEG/upload_86659845703144280985584b1-2698-4b6d-b6bb-f0bbad3c29fe.jpg?type=f228_128_wp"},{"title":"[2 Kids Room(투키즈룸)] Teaser Video","contents":"Stray Kids","link":"https://www.vlive.tv/video/275044","retrieved":1642607048139,"image":"https://v-phinf.pstatic.net/20220119_193/1642584432948r3ASs_PNG/upload_588470956233802224a5c5f6f-df00-4201-bcbf-6d939481e942.png?type=f228_128_wp"},{"title":"[GOING SEVENTEEN SPECIAL] 고잉 코멘터리 (GOING COMMENTARY)","contents":"SEVENTEEN","link":"https://www.vlive.tv/video/275046","retrieved":1642650059668,"image":"https://v-phinf.pstatic.net/20220119_203/1642584673838dgp1P_JPEG/upload_58854216796429316f933fd5e-a8ea-4d8e-9322-a90e97b94048.jpg?type=f228_128_wp"},{"title":"🎥 MOON BYUL 3RD MINI ALBUM 발매 기념 VLIVE 🎞","contents":"MAMAMOO","link":"https://www.vlive.tv/video/275068","retrieved":1642664348277,"image":"https://v-phinf.pstatic.net/20220120_202/1642606208816G6heK_JPEG/1259176845905866956165020f-592b-4657-a7f8-bca32c05eca6.jpg?type=f228_128_wp"}]}