{"title":"V LIVE ─ 일정표","url":"https://www.vlive.tv/upcoming?lang=ko","favicon":"https://www.vlive.tv/favicon.ico","elements":[{"title":"굿모닝 라이브","contents":"오전 12:07","link":"https://www.vlive.tv/video/290013","retrieved":1661038998306,"image":"https://v-phinf.pstatic.net/20220821_294/16610382862505jqVg_JPEG/54656062529098875fc99bc39-88b8-4a6a-86be-f91968926f17.jpg?type=f228_128"},{"title":"밥 먹어요","contents":"오전 4:14","link":"https://www.vlive.tv/video/290014","retrieved":1661055306960,"image":"https://v-phinf.pstatic.net/20220821_264/1661055276693x2s2f_JPEG/a08bd73a-2107-11ed-aee9-505dac8c38f5_03.jpg?type=f228_128"}]}