{"title":"V LIVE ─ 일정표","url":"https://www.vlive.tv/upcoming?lang=ko","favicon":"https://www.vlive.tv/favicon.ico","elements":[{"title":"[3차 티저] 김희선X로운, 사람 살리는 저승사자들의 '내일' 되찾기 프로젝트! MBC 금토드라마 '내일' 4월 1일 (금) 첫 방송!","contents":"오전 12:00","link":"https://www.vlive.tv/video/279878","retrieved":1648346956434,"image":"https://v-phinf.pstatic.net/20220324_42/1648077528985ES7he_JPEG/upload_921572595457829206020c9b1-218e-46f3-a442-ba42dd7c5f21.jpg?type=f228_128"},{"title":"[D-2] 임상현 - ‘달콤하게, 따뜻하게, 부드럽게’","contents":"오전 3:00","link":"https://www.vlive.tv/video/279872","retrieved":1648350252582,"image":"https://v-phinf.pstatic.net/20220324_296/1648048448022NvvpB_JPEG/upload_921281556568872185e4c3657-43bb-472b-a15f-ab82589947ae.jpg?type=f228_128"},{"title":"(여자)아이들((G)I-DLE) - I-TALK #93 : 'TOMBOY' 뮤비 촬영 현장 비하인드 Part 2","contents":"오전 3:00","link":"https://www.vlive.tv/video/280055","retrieved":1648350252583,"image":"https://v-phinf.pstatic.net/20220325_40/1648217425346mQNzO_JPEG/upload_92297093114432122a0a67411-4058-4353-99b5-43c53179b622.jpg?type=f228_128"},{"title":"N.Flying 공식 팬클럽 [N.Fia] 3기 모집","contents":"오전 3:00","link":"https://www.vlive.tv/video/280072","retrieved":1648350252584,"image":"https://v-phinf.pstatic.net/20220326_210/16482799281196qYEU_JPEG/upload_923594998197470751793a618-bf08-4ad0-bb51-32d2929d2b7e.jpg?type=f228_128"},{"title":"[직캠] 브레이브걸스(Brave Girls) 민영(MINYOUNG) - Thank You @ [THANK YOU] SHOWCASE","contents":"오전 3:00","link":"https://www.vlive.tv/video/280096","retrieved":1648350252587,"image":"https://v-phinf.pstatic.net/20220326_185/1648295861846Dc3ED_JPEG/upload_92375563028414955369f0329-476e-49b7-a739-cc045c20fa49.jpg?type=f228_128"},{"title":"[직캠] 브레이브걸스(Brave Girls) 유정(YUJEONG) - Thank You @ [THANK YOU] SHOWCASE","contents":"오전 3:00","link":"https://www.vlive.tv/video/280098","retrieved":1648350252588,"image":"https://v-phinf.pstatic.net/20220326_237/1648296068211WBCAJ_JPEG/upload_64565665406524517fabe2336-4f6d-4291-a69c-cade5aea14bf.jpg?type=f228_128"},{"title":"[직캠] 브레이브걸스(Brave Girls) 은지(EUNJI) - Thank You @ [THANK YOU] SHOWCASE","contents":"오전 3:00","link":"https://www.vlive.tv/video/280099","retrieved":1648350252589,"image":"https://v-phinf.pstatic.net/20220326_155/1648296511705BBP2Q_JPEG/upload_92376151287062906cfb0cbfc-eb68-49d4-b6df-adf1f7795695.jpg?type=f228_128"},{"title":"[직캠] 브레이브걸스(Brave Girls) 유나(YUNA) - Thank You @ [THANK YOU] SHOWCASE","contents":"오전 3:00","link":"https://www.vlive.tv/video/280100","retrieved":1648350252589,"image":"https://v-phinf.pstatic.net/20220326_94/1648296785759EgTTj_JPEG/upload_6456638775703265798e1bd48-c913-491f-ac7a-14fa170fb743.jpg?type=f228_128"},{"title":"자.다시!!","contents":"오전 4:10","link":"https://www.vlive.tv/video/280111","retrieved":1648356632975,"image":"https://v-phinf.pstatic.net/20220327_85/1648354209803gMK7c_JPEG/1612298237913688972bb15fc0-6e7c-4661-9a38-c12d98d0259c.jpg?type=f228_128"},{"title":"세상이 되어줘서 고마워","contents":"오전 4:12","link":"https://www.vlive.tv/video/280110","retrieved":1648352751151,"image":"https://v-phinf.pstatic.net/20220327_152/1648350479741BKfBi_JPEG/7040291826967470704027ffa-920a-40e4-9e85-3592ebc60d70.jpg?type=f228_128"},{"title":"Sunday Morning☀️","contents":"오전 4:33","link":"https://www.vlive.tv/video/280112","retrieved":1648356632980,"image":"https://vlive-thumb.pstatic.net/live/280112/thumb?type=f228_128"}]}